civo/__init__.py
civo/charges.py
civo/civo.py
civo/dns.py
civo/exceptions.py
civo/firewall.py
civo/intances.py
civo/kubernetes.py
civo/loadbalance.py
civo/networks.py
civo/quota.py
civo/regions.py
civo/size.py
civo/snapshots.py
civo/ssh.py
civo/templates.py
civo/utils.py
civo/volumes.py
civo/webhook.py
unit_test/__init__.py
unit_test/test_civo.py
unit_test/test_kubernetes.py
civo-1.0.8.dist-info/LICENSE
civo-1.0.8.dist-info/METADATA
civo-1.0.8.dist-info/WHEEL
civo-1.0.8.dist-info/top_level.txt
civo-1.0.8.dist-info/RECORD
