Metadata-Version: 2.1
Name: civo
Version: 1.0.8
Summary: Wrapper for civo api
Home-page: https://github.com/civo/client-python
Author: Alejandro JNM
Author-email: alejandrojnm@gmail.com
License: MIT License
Platform: UNKNOWN
Classifier: Development Status :: 5 - Production/Stable
Classifier: License :: OSI Approved :: MIT License
Classifier: Natural Language :: English
Classifier: Programming Language :: Python
Classifier: Programming Language :: Python :: 3.6
Classifier: Programming Language :: Python :: 3.7
Requires-Dist: requests
